<?xml version="1.0" encoding="UTF-8"?>

<commandSetRoot xmlns:xsi="http://www.w3.org/2001/XMLSchema-instance"
				xsi:schemaLocation='commandSet.xsd'>
  <commandSet type="serial">
    <state>incomplete</state>
    <name>clovr_blastall.prestart</name>
    <command>
      <name>Tag data</name>
      <type>RunUnixCommand</type>
      <executable>tagData.py</executable>
      <arg>--name local --tag-name $;INPUT_TAG$; --overwrite --recursive $;INPUT_FILES$;</arg>
    </command>
  </commandSet>
</commandSetRoot>
